{
  "kind": "collectionType",
  "collectionName": "recipes",
  "info": {
    "singularName": "recipe",
    "pluralName": "recipes",
    "displayName": "recipe",
    "description": ""
  },
  "options": {
    "draftAndPublish": false
  },
  "pluginOptions": {},
  "attributes": {
    "title": {
      "type": "string"
    },
    "videoURL": {
      "type": "string"
    },
    "order": {
      "type": "text"
    },
    "uploader": {
      "type": "string"
    },
    "measure": {
      "type": "json"
    },
    "ingredients": {
      "type": "string"
    },
    "tag": {
      "type": "string"
    }
  }
}
